consent_broker/__init__.py
consent_broker-0.0.1.dist-info/LICENSE
consent_broker-0.0.1.dist-info/WHEEL
consent_broker-0.0.1.dist-info/METADATA
consent_broker-0.0.1.dist-info/RECORD
